cairosvg/VERSION
cairosvg/__init__.py
cairosvg/__main__.py
cairosvg/bounding_box.py
cairosvg/colors.py
cairosvg/css.py
cairosvg/defs.py
cairosvg/features.py
cairosvg/helpers.py
cairosvg/image.py
cairosvg/parser.py
cairosvg/path.py
cairosvg/shapes.py
cairosvg/surface.py
cairosvg/svg.py
cairosvg/test_api.py
cairosvg/text.py
cairosvg/url.py
cairosvg-2.8.1.dist-info/licenses/LICENSE
cairosvg-2.8.1.dist-info/METADATA
cairosvg-2.8.1.dist-info/WHEEL
cairosvg-2.8.1.dist-info/entry_points.txt
cairosvg-2.8.1.dist-info/top_level.txt
cairosvg-2.8.1.dist-info/RECORD
