Metadata-Version: 2.4
Name: CairoSVG
Version: 2.8.1
Summary: A Simple SVG Converter based on Cairo
Home-page: https://courtbouillon.org/cairosvg
Author: Guillaume Ayoub
Author-email: contact@courtbouillon.org
License: LGPL-3.0-or-later
Project-URL: Documentation, https://cairosvg.org/documentation/
Project-URL: Code, https://github.com/Kozea/CairoSVG/
Project-URL: Issue tracker, https://github.com/Kozea/CairoSVG/issues
Project-URL: Donation, https://opencollective.com/courtbouillon
Keywords: svg,converter,cairo,pdf,png,postscript
Platform: Linux
Platform: macOS
Platform: Windows
Classifier: Development Status :: 5 - Production/Stable
Classifier: Environment :: Console
Classifier: Intended Audience :: End Users/Desktop
Classifier: Operating System :: OS Independent
Classifier: Programming Language :: Python :: 3 :: Only
Classifier: Programming Language :: Python :: 3.9
Classifier: Programming Language :: Python :: 3.10
Classifier: Programming Language :: Python :: 3.11
Classifier: Programming Language :: Python :: 3.12
Classifier: Programming Language :: Python :: 3.13
Classifier: Topic :: Multimedia :: Graphics :: Graphics Conversion
Requires-Python: >=3.9
License-File: LICENSE
Requires-Dist: cairocffi
Requires-Dist: cssselect2
Requires-Dist: defusedxml
Requires-Dist: pillow
Requires-Dist: tinycss2
Provides-Extra: doc
Requires-Dist: sphinx; extra == "doc"
Requires-Dist: sphinx_rtd_theme; extra == "doc"
Provides-Extra: test
Requires-Dist: pytest; extra == "test"
Requires-Dist: flake8; extra == "test"
Requires-Dist: isort; extra == "test"
Dynamic: license-file
